fa_filter/__init__.py
fa_filter/core/exceptions.py
fa_filter/sqlalchemy/filter.py
fa_filter-0.2.2.dist-info/licenses/LICENSE
fa_filter-0.2.2.dist-info/METADATA
fa_filter-0.2.2.dist-info/WHEEL
fa_filter-0.2.2.dist-info/top_level.txt
fa_filter-0.2.2.dist-info/RECORD
