Metadata-Version: 2.4
Name: fa-filter
Version: 0.2.2
Summary: Filter, sort, limit, and offset by pydantic
Requires-Python: >=3.12
License-File: LICENSE
Requires-Dist: pydantic>=2.11.4
Requires-Dist: sqlalchemy>=2.0.41
Dynamic: license-file
